{
  "topic": "Education",
  "words": [
    {
      "word": "colegio bilingüe",
      "translation": "colegio bilingüe",
      "example": "Слово «colegio bilingüe» полезно."
    },
    {
      "word": "colegio religioso",
      "translation": "colegio religioso",
      "example": "Слово «colegio religioso» полезно."
    },
    {
      "word": "colegio laico",
      "translation": "colegio laico",
      "example": "Слово «colegio laico» полезно."
    },
    {
      "word": "escuela superior",
      "translation": "escuela superior",
      "example": "Слово «escuela superior» полезно."
    },
    {
      "word": "alumnado",
      "translation": "alumnado",
      "example": "Слово «alumnado» полезно."
    },
    {
      "word": "profesorado",
      "translation": "profesorado",
      "example": "Слово «profesorado» полезно."
    },
    {
      "word": "catedrático",
      "translation": "catedrático",
      "example": "Слово «catedrático» полезно."
    },
    {
      "word": "rector",
      "translation": "rector",
      "example": "Слово «rector» полезно."
    },
    {
      "word": "jefe de estudios",
      "translation": "jefe de estudios",
      "example": "Слово «jefe de estudios» полезно."
    },
    {
      "word": "maestro",
      "translation": "maestro",
      "example": "Слово «maestro» полезно."
    },
    {
      "word": "tutor",
      "translation": "tutor",
      "example": "Слово «tutor» полезно."
    },
    {
      "word": "director de tesis",
      "translation": "director de tesis",
      "example": "Слово «director de tesis» полезно."
    },
    {
      "word": "delegado de curso",
      "translation": "delegado de curso",
      "example": "Слово «delegado de curso» полезно."
    },
    {
      "word": "conferenciante",
      "translation": "conferenciante",
      "example": "Слово «conferenciante» полезно."
    },
    {
      "word": "universitario",
      "translation": "universitario",
      "example": "Слово «universitario» полезно."
    },
    {
      "word": "asociación de profesores",
      "translation": "asociación de profesores",
      "example": "Слово «asociación de profesores» полезно."
    },
    {
      "word": "asociación de antiguos alumnos",
      "translation": "asociación de antiguos alumnos",
      "example": "Слово «asociación de antiguos alumnos» полезно."
    },
    {
      "word": "asignatura obligatoria",
      "translation": "asignatura obligatoria",
      "example": "Слово «asignatura obligatoria» полезно."
    },
    {
      "word": "asignatura común",
      "translation": "asignatura común",
      "example": "Слово «asignatura común» полезно."
    },
    {
      "word": "materia trimestral",
      "translation": "materia trimestral",
      "example": "Слово «materia trimestral» полезно."
    },
    {
      "word": "materia anual",
      "translation": "materia anual",
      "example": "Слово «materia anual» полезно."
    },
    {
      "word": "curso elemental",
      "translation": "curso elemental",
      "example": "Слово «curso elemental» полезно."
    },
    {
      "word": "curso obligatorio",
      "translation": "curso obligatorio",
      "example": "Слово «curso obligatorio» полезно."
    },
    {
      "word": "curso optativo",
      "translation": "curso optativo",
      "example": "Слово «curso optativo» полезно."
    },
    {
      "word": "formación continua",
      "translation": "formación continua",
      "example": "Слово «formación continua» полезно."
    },
    {
      "word": "formación permanente",
      "translation": "formación permanente",
      "example": "Слово «formación permanente» полезно."
    },
    {
      "word": "educación primaria",
      "translation": "educación primaria",
      "example": "Слово «educación primaria» полезно."
    },
    {
      "word": "educación secundaria",
      "translation": "educación secundaria",
      "example": "Слово «educación secundaria» полезно."
    },
    {
      "word": "educación universitaria",
      "translation": "educación universitaria",
      "example": "Слово «educación universitaria» полезно."
    },
    {
      "word": "educación superior",
      "translation": "educación superior",
      "example": "Слово «educación superior» полезно."
    },
    {
      "word": "educación a adultos",
      "translation": "educación a adultos",
      "example": "Слово «educación a adultos» полезно."
    },
    {
      "word": "estudios primarios",
      "translation": "estudios primarios",
      "example": "Слово «estudios primarios» полезно."
    },
    {
      "word": "estudios secundarios",
      "translation": "estudios secundarios",
      "example": "Слово «estudios secundarios» полезно."
    },
    {
      "word": "estudios superiores",
      "translation": "estudios superiores",
      "example": "Слово «estudios superiores» полезно."
    },
    {
      "word": "estudios universitarios",
      "translation": "estudios universitarios",
      "example": "Слово «estudios universitarios» полезно."
    },
    {
      "word": "educación pública",
      "translation": "educación pública",
      "example": "Слово «educación pública» полезно."
    },
    {
      "word": "educación privada",
      "translation": "educación privada",
      "example": "Слово «educación privada» полезно."
    },
    {
      "word": "educación religiosa",
      "translation": "educación religiosa",
      "example": "Слово «educación religiosa» полезно."
    },
    {
      "word": "educación laica",
      "translation": "educación laica",
      "example": "Слово «educación laica» полезно."
    },
    {
      "word": "enseñanza primaria",
      "translation": "enseñanza primaria",
      "example": "Слово «enseñanza primaria» полезно."
    },
    {
      "word": "enseñanza secundaria",
      "translation": "enseñanza secundaria",
      "example": "Слово «enseñanza secundaria» полезно."
    },
    {
      "word": "enseñanza universitaria",
      "translation": "enseñanza universitaria",
      "example": "Слово «enseñanza universitaria» полезно."
    },
    {
      "word": "enseñanza superior",
      "translation": "enseñanza superior",
      "example": "Слово «enseñanza superior» полезно."
    },
    {
      "word": "enseñanza a adultos",
      "translation": "enseñanza a adultos",
      "example": "Слово «enseñanza a adultos» полезно."
    },
    {
      "word": "enseñanza pública",
      "translation": "enseñanza pública",
      "example": "Слово «enseñanza pública» полезно."
    },
    {
      "word": "enseñanza privada",
      "translation": "enseñanza privada",
      "example": "Слово «enseñanza privada» полезно."
    },
    {
      "word": "enseñanza religiosa",
      "translation": "enseñanza religiosa",
      "example": "Слово «enseñanza religiosa» полезно."
    },
    {
      "word": "enseñanza laica",
      "translation": "enseñanza laica",
      "example": "Слово «enseñanza laica» полезно."
    },
    {
      "word": "enseñanza presencial",
      "translation": "enseñanza presencial",
      "example": "Слово «enseñanza presencial» полезно."
    },
    {
      "word": "enseñanza virtual",
      "translation": "enseñanza virtual",
      "example": "Слово «enseñanza virtual» полезно."
    },
    {
      "word": "enseñanza a distancia",
      "translation": "enseñanza a distancia",
      "example": "Слово «enseñanza a distancia» полезно."
    },
    {
      "word": "curso presencial",
      "translation": "curso presencial",
      "example": "Слово «curso presencial» полезно."
    },
    {
      "word": "curso virtual",
      "translation": "curso virtual",
      "example": "Слово «curso virtual» полезно."
    },
    {
      "word": "curso a distancia",
      "translation": "curso a distancia",
      "example": "Слово «curso a distancia» полезно."
    },
    {
      "word": "curso intensivo",
      "translation": "curso intensivo",
      "example": "Слово «curso intensivo» полезно."
    },
    {
      "word": "curso de iniciación",
      "translation": "curso de iniciación",
      "example": "Слово «curso de iniciación» полезно."
    },
    {
      "word": "curso de perfeccionamiento",
      "translation": "curso de perfeccionamiento",
      "example": "Слово «curso de perfeccionamiento» полезно."
    },
    {
      "word": "seminario",
      "translation": "seminario",
      "example": "Слово «seminario» полезно."
    },
    {
      "word": "congreso",
      "translation": "congreso",
      "example": "Слово «congreso» полезно."
    },
    {
      "word": "ofrecer educación superior",
      "translation": "ofrecer educación superior",
      "example": "Слово «ofrecer educación superior» полезно."
    },
    {
      "word": "ofrecer educación universitaria",
      "translation": "ofrecer educación universitaria",
      "example": "Слово «ofrecer educación universitaria» полезно."
    },
    {
      "word": "recibir educación superior",
      "translation": "recibir educación superior",
      "example": "Слово «recibir educación superior» полезно."
    },
    {
      "word": "recibir educación universitaria",
      "translation": "recibir educación universitaria",
      "example": "Слово «recibir educación universitaria» полезно."
    },
    {
      "word": "solicitar una beca",
      "translation": "solicitar una beca",
      "example": "Слово «solicitar una beca» полезно."
    },
    {
      "word": "solicitar una plaza",
      "translation": "solicitar una plaza",
      "example": "Слово «solicitar una plaza» полезно."
    },
    {
      "word": "conceder una beca",
      "translation": "conceder una beca",
      "example": "Слово «conceder una beca» полезно."
    },
    {
      "word": "conceder una plaza",
      "translation": "conceder una plaza",
      "example": "Слово «conceder una plaza» полезно."
    },
    {
      "word": "disfrutar de una beca",
      "translation": "disfrutar de una beca",
      "example": "Слово «disfrutar de una beca» полезно."
    },
    {
      "word": "educación",
      "translation": "educación",
      "example": "Слово «educación» полезно."
    },
    {
      "word": "enseñanza",
      "translation": "enseñanza",
      "example": "Слово «enseñanza» полезно."
    },
    {
      "word": "aprendizaje",
      "translation": "aprendizaje",
      "example": "Слово «aprendizaje» полезно."
    },
    {
      "word": "alumno brillante",
      "translation": "alumno brillante",
      "example": "Слово «alumno brillante» полезно."
    },
    {
      "word": "alumno estudioso",
      "translation": "alumno estudioso",
      "example": "Слово «alumno estudioso» полезно."
    },
    {
      "word": "alumno conflictivo",
      "translation": "alumno conflictivo",
      "example": "Слово «alumno conflictivo» полезно."
    },
    {
      "word": "didáctico",
      "translation": "didáctico",
      "example": "Слово «didáctico» полезно."
    },
    {
      "word": "educativo",
      "translation": "educativo",
      "example": "Слово «educativo» полезно."
    },
    {
      "word": "memorizar",
      "translation": "memorizar",
      "example": "Слово «memorizar» полезно."
    },
    {
      "word": "reflexionar",
      "translation": "reflexionar",
      "example": "Слово «reflexionar» полезно."
    },
    {
      "word": "deducir",
      "translation": "deducir",
      "example": "Слово «deducir» полезно."
    },
    {
      "word": "sacar conclusiones",
      "translation": "sacar conclusiones",
      "example": "Слово «sacar conclusiones» полезно."
    },
    {
      "word": "quedarse en blanco",
      "translation": "quedarse en blanco",
      "example": "Слово «quedarse en blanco» полезно."
    },
    {
      "word": "formarse",
      "translation": "formarse",
      "example": "Слово «formarse» полезно."
    },
    {
      "word": "educarse",
      "translation": "educarse",
      "example": "Слово «educarse» полезно."
    },
    {
      "word": "recibir clases",
      "translation": "recibir clases",
      "example": "Слово «recibir clases» полезно."
    },
    {
      "word": "tomar clases",
      "translation": "tomar clases",
      "example": "Слово «tomar clases» полезно."
    },
    {
      "word": "examen parcial",
      "translation": "examen parcial",
      "example": "Слово «examen parcial» полезно."
    },
    {
      "word": "examen final",
      "translation": "examen final",
      "example": "Слово «examen final» полезно."
    },
    {
      "word": "examen cuatrimestral",
      "translation": "examen cuatrimestral",
      "example": "Слово «examen cuatrimestral» полезно."
    },
    {
      "word": "examen anual",
      "translation": "examen anual",
      "example": "Слово «examen anual» полезно."
    },
    {
      "word": "prueba parcial",
      "translation": "prueba parcial",
      "example": "Слово «prueba parcial» полезно."
    },
    {
      "word": "prueba final",
      "translation": "prueba final",
      "example": "Слово «prueba final» полезно."
    },
    {
      "word": "prueba cuatrimestral",
      "translation": "prueba cuatrimestral",
      "example": "Слово «prueba cuatrimestral» полезно."
    },
    {
      "word": "prueba anual",
      "translation": "prueba anual",
      "example": "Слово «prueba anual» полезно."
    },
    {
      "word": "control parcial",
      "translation": "control parcial",
      "example": "Слово «control parcial» полезно."
    },
    {
      "word": "control final",
      "translation": "control final",
      "example": "Слово «control final» полезно."
    },
    {
      "word": "control cuatrimestral",
      "translation": "control cuatrimestral",
      "example": "Слово «control cuatrimestral» полезно."
    },
    {
      "word": "control anual",
      "translation": "control anual",
      "example": "Слово «control anual» полезно."
    },
    {
      "word": "nota media",
      "translation": "nota media",
      "example": "Слово «nota media» полезно."
    },
    {
      "word": "nota final",
      "translation": "nota final",
      "example": "Слово «nota final» полезно."
    },
    {
      "word": "nota justa",
      "translation": "nota justa",
      "example": "Слово «nota justa» полезно."
    },
    {
      "word": "nota injusta",
      "translation": "nota injusta",
      "example": "Слово «nota injusta» полезно."
    },
    {
      "word": "nota alta",
      "translation": "nota alta",
      "example": "Слово «nota alta» полезно."
    },
    {
      "word": "nota baja",
      "translation": "nota baja",
      "example": "Слово «nota baja» полезно."
    },
    {
      "word": "evaluación parcial",
      "translation": "evaluación parcial",
      "example": "Слово «evaluación parcial» полезно."
    },
    {
      "word": "evaluación final",
      "translation": "evaluación final",
      "example": "Слово «evaluación final» полезно."
    },
    {
      "word": "autoevaluación",
      "translation": "autoevaluación",
      "example": "Слово «autoevaluación» полезно."
    },
    {
      "word": "prepararse para un examen",
      "translation": "prepararse para un examen",
      "example": "Слово «prepararse para un examen» полезно."
    },
    {
      "word": "pasar un examen",
      "translation": "pasar un examen",
      "example": "Слово «pasar un examen» полезно."
    },
    {
      "word": "presentarse a un examen",
      "translation": "presentarse a un examen",
      "example": "Слово «presentarse a un examen» полезно."
    },
    {
      "word": "examinarse",
      "translation": "examinarse",
      "example": "Слово «examinarse» полезно."
    },
    {
      "word": "hacer una prueba de nivel",
      "translation": "hacer una prueba de nivel",
      "example": "Слово «hacer una prueba de nivel» полезно."
    },
    {
      "word": "sacar buenas notas",
      "translation": "sacar buenas notas",
      "example": "Слово «sacar buenas notas» полезно."
    },
    {
      "word": "sacar malas notas",
      "translation": "sacar malas notas",
      "example": "Слово «sacar malas notas» полезно."
    },
    {
      "word": "sacar un sobresaliente",
      "translation": "sacar un sobresaliente",
      "example": "Слово «sacar un sobresaliente» полезно."
    },
    {
      "word": "sacar un notable",
      "translation": "sacar un notable",
      "example": "Слово «sacar un notable» полезно."
    },
    {
      "word": "sacar un cinco",
      "translation": "sacar un cinco",
      "example": "Слово «sacar un cinco» полезно."
    },
    {
      "word": "poner notas",
      "translation": "poner notas",
      "example": "Слово «poner notas» полезно."
    },
    {
      "word": "pasar de curso",
      "translation": "pasar de curso",
      "example": "Слово «pasar de curso» полезно."
    },
    {
      "word": "tener una asignatura pendiente",
      "translation": "tener una asignatura pendiente",
      "example": "Слово «tener una asignatura pendiente» полезно."
    },
    {
      "word": "quedar una asignatura pendiente",
      "translation": "quedar una asignatura pendiente",
      "example": "Слово «quedar una asignatura pendiente» полезно."
    },
    {
      "word": "pedir revisión de examen",
      "translation": "pedir revisión de examen",
      "example": "Слово «pedir revisión de examen» полезно."
    },
    {
      "word": "graduado escolar",
      "translation": "graduado escolar",
      "example": "Слово «graduado escolar» полезно."
    },
    {
      "word": "formación profesional",
      "translation": "formación profesional",
      "example": "Слово «formación profesional» полезно."
    },
    {
      "word": "hacer estudios primarios",
      "translation": "hacer estudios primarios",
      "example": "Слово «hacer estudios primarios» полезно."
    },
    {
      "word": "hacer estudios secundarios",
      "translation": "hacer estudios secundarios",
      "example": "Слово «hacer estudios secundarios» полезно."
    },
    {
      "word": "hacer estudios universitarios",
      "translation": "hacer estudios universitarios",
      "example": "Слово «hacer estudios universitarios» полезно."
    },
    {
      "word": "tener estudios primarios",
      "translation": "tener estudios primarios",
      "example": "Слово «tener estudios primarios» полезно."
    },
    {
      "word": "tener estudios secundarios",
      "translation": "tener estudios secundarios",
      "example": "Слово «tener estudios secundarios» полезно."
    },
    {
      "word": "tener estudios universitarios",
      "translation": "tener estudios universitarios",
      "example": "Слово «tener estudios universitarios» полезно."
    },
    {
      "word": "licenciarse",
      "translation": "licenciarse",
      "example": "Слово «licenciarse» полезно."
    },
    {
      "word": "titularse",
      "translation": "titularse",
      "example": "Слово «titularse» полезно."
    },
    {
      "word": "doctorarse",
      "translation": "doctorarse",
      "example": "Слово «doctorarse» полезно."
    },
    {
      "word": "hacer la tesis doctoral",
      "translation": "hacer la tesis doctoral",
      "example": "Слово «hacer la tesis doctoral» полезно."
    },
    {
      "word": "tener una licenciatura",
      "translation": "tener una licenciatura",
      "example": "Слово «tener una licenciatura» полезно."
    },
    {
      "word": "tener una diplomatura",
      "translation": "tener una diplomatura",
      "example": "Слово «tener una diplomatura» полезно."
    },
    {
      "word": "tener un doctorado",
      "translation": "tener un doctorado",
      "example": "Слово «tener un doctorado» полезно."
    },
    {
      "word": "tener la especialidad en",
      "translation": "tener la especialidad en",
      "example": "Слово «tener la especialidad en» полезно."
    },
    {
      "word": "ser licenciado en Empresariales",
      "translation": "ser licenciado en Empresariales",
      "example": "Слово «ser licenciado en Empresariales» полезно."
    },
    {
      "word": "ser licenciado en Filología",
      "translation": "ser licenciado en Filología",
      "example": "Слово «ser licenciado en Filología» полезно."
    },
    {
      "word": "ser doctor en Empresariales",
      "translation": "ser doctor en Empresariales",
      "example": "Слово «ser doctor en Empresariales» полезно."
    },
    {
      "word": "ser doctor en Filología",
      "translation": "ser doctor en Filología",
      "example": "Слово «ser doctor en Filología» полезно."
    },
    {
      "word": "abandonar los estudios",
      "translation": "abandonar los estudios",
      "example": "Слово «abandonar los estudios» полезно."
    },
    {
      "word": "dejar los estudios",
      "translation": "dejar los estudios",
      "example": "Слово «dejar los estudios» полезно."
    },
    {
      "word": "continuar los estudios",
      "translation": "continuar los estudios",
      "example": "Слово «continuar los estudios» полезно."
    },
    {
      "word": "completar los estudios",
      "translation": "completar los estudios",
      "example": "Слово «completar los estudios» полезно."
    },
    {
      "word": "plantear una duda",
      "translation": "plantear una duda",
      "example": "Слово «plantear una duda» полезно."
    },
    {
      "word": "resolver una duda",
      "translation": "resolver una duda",
      "example": "Слово «resolver una duda» полезно."
    },
    {
      "word": "aplicar una fórmula",
      "translation": "aplicar una fórmula",
      "example": "Слово «aplicar una fórmula» полезно."
    },
    {
      "word": "deducir una regla",
      "translation": "deducir una regla",
      "example": "Слово «deducir una regla» полезно."
    },
    {
      "word": "seguir una regla",
      "translation": "seguir una regla",
      "example": "Слово «seguir una regla» полезно."
    },
    {
      "word": "analizar un tema",
      "translation": "analizar un tema",
      "example": "Слово «analizar un tema» полезно."
    },
    {
      "word": "debatir un tema",
      "translation": "debatir un tema",
      "example": "Слово «debatir un tema» полезно."
    },
    {
      "word": "discutir un tema",
      "translation": "discutir un tema",
      "example": "Слово «discutir un tema» полезно."
    },
    {
      "word": "consultar",
      "translation": "consultar",
      "example": "Слово «consultar» полезно."
    },
    {
      "word": "cartucho de tinta",
      "translation": "cartucho de tinta",
      "example": "Слово «cartucho de tinta» полезно."
    },
    {
      "word": "grapadora",
      "translation": "grapadora",
      "example": "Слово «grapadora» полезно."
    },
    {
      "word": "grapa",
      "translation": "grapa",
      "example": "Слово «grapa» полезно."
    },
    {
      "word": "clip",
      "translation": "clip",
      "example": "Слово «clip» полезно."
    },
    {
      "word": "celo",
      "translation": "celo",
      "example": "Слово «celo» полезно."
    },
    {
      "word": "borrador",
      "translation": "borrador",
      "example": "Слово «borrador» полезно."
    },
    {
      "word": "retroproyector",
      "translation": "retroproyector",
      "example": "Слово «retroproyector» полезно."
    },
    {
      "word": "transparencia",
      "translation": "transparencia",
      "example": "Слово «transparencia» полезно."
    },
    {
      "word": "diapositiva",
      "translation": "diapositiva",
      "example": "Слово «diapositiva» полезно."
    },
    {
      "word": "papel cuadriculado",
      "translation": "papel cuadriculado",
      "example": "Слово «papel cuadriculado» полезно."
    },
    {
      "word": "cartulina",
      "translation": "cartulina",
      "example": "Слово «cartulina» полезно."
    },
    {
      "word": "rotulador fluorescente",
      "translation": "rotulador fluorescente",
      "example": "Слово «rotulador fluorescente» полезно."
    },
    {
      "word": "rotulador de punta fina",
      "translation": "rotulador de punta fina",
      "example": "Слово «rotulador de punta fina» полезно."
    },
    {
      "word": "rotulador de punta gruesa",
      "translation": "rotulador de punta gruesa",
      "example": "Слово «rotulador de punta gruesa» полезно."
    },
    {
      "word": "poner una transparencia",
      "translation": "poner una transparencia",
      "example": "Слово «poner una transparencia» полезно."
    },
    {
      "word": "poner una diapositiva",
      "translation": "poner una diapositiva",
      "example": "Слово «poner una diapositiva» полезно."
    },
    {
      "word": "proyectar una transparencia",
      "translation": "proyectar una transparencia",
      "example": "Слово «proyectar una transparencia» полезно."
    },
    {
      "word": "proyectar una diapositiva",
      "translation": "proyectar una diapositiva",
      "example": "Слово «proyectar una diapositiva» полезно."
    }
  ]
}